chat/__init__.py
chat/py.typed
chat/cli/__init__.py
chat/cli/entry_point.py
chat/context/__init__.py
chat/context/context.py
chat/main/__init__.py
chat/main/chat.py
chat/main/history.py
chat/main/main.py
chat/models/__init__.py
chat/models/config.py
chat/models/messages.py
chat/models/options.py
chat/models/path.py
powerchat_cli-0.1.6.dist-info/LICENSE
powerchat_cli-0.1.6.dist-info/METADATA
powerchat_cli-0.1.6.dist-info/WHEEL
powerchat_cli-0.1.6.dist-info/entry_points.txt
powerchat_cli-0.1.6.dist-info/top_level.txt
powerchat_cli-0.1.6.dist-info/RECORD
