Metadata-Version: 2.1
Name: powerchat-cli
Version: 0.1.6
Summary: CLI interface for local LLM assistant
Author-email: Quinten Roets <qdr2104@columbia.edu>
License: MIT
Project-URL: Source Code, https://github.com/quintenroets/chat
Requires-Python: >=3.10
License-File: LICENSE
Requires-Dist: langchain-ollama<1,>=0.1.1
Requires-Dist: package-utils[context]<1,>=0.6.1
Requires-Dist: powercli<1,>=0.3.2
Provides-Extra: dev
Requires-Dist: package-dev-tools<1,>=0.5.11; extra == "dev"
Requires-Dist: package-dev-utils<1,>=0.1.6; extra == "dev"
